my_own_package/__init__.py
mircix_own_package-1.0.0.dist-info/METADATA
mircix_own_package-1.0.0.dist-info/WHEEL
mircix_own_package-1.0.0.dist-info/top_level.txt
mircix_own_package-1.0.0.dist-info/RECORD
